dagworks/__init__.py
dagworks/adapters.py
dagworks/driver.py
dagworks/api/__init__.py
dagworks/api/clients.py
dagworks/api/constants.py
dagworks/api/projecttypes.py
dagworks/cli/__init__.py
dagworks/cli/cli.py
dagworks/cli/initialize.py
dagworks/cli/templates/__init__.py
dagworks/cli/templates/common/.env.jinja2
dagworks/cli/templates/common/README.md.jinja2
dagworks/cli/templates/common/requirements.txt.jinja2
dagworks/cli/templates/common/run.py.jinja2
dagworks/cli/templates/common/run.sh.jinja2
dagworks/cli/templates/data_processing/template_data.json
dagworks/cli/templates/data_processing/components/__init__.py
dagworks/cli/templates/data_processing/components/_run.py
dagworks/cli/templates/data_processing/components/common.py
dagworks/cli/templates/data_processing/components/data_loader.py
dagworks/cli/templates/data_processing/config/config.json
dagworks/cli/templates/data_processing/data/order_details.csv
dagworks/cli/templates/data_processing/data/orders_new.csv
dagworks/cli/templates/data_processing/data/orders_old.csv
dagworks/cli/templates/hello_world/template_data.json
dagworks/cli/templates/hello_world/components/__init__.py
dagworks/cli/templates/hello_world/components/transforms.py
dagworks/cli/templates/hello_world/data/signups.csv
dagworks/cli/templates/hello_world/data/spend.csv
dagworks/cli/templates/machine_learning/template_data.json
dagworks/cli/templates/machine_learning/components/__init__.py
dagworks/cli/templates/machine_learning/components/_run.py
dagworks/cli/templates/machine_learning/components/feature_transforms.py
dagworks/cli/templates/machine_learning/components/iris_loader.py
dagworks/cli/templates/machine_learning/components/model_fitting.py
dagworks/cli/templates/machine_learning/components/models.py
dagworks/cli/templates/time_series_feature_engineering/template_data.json
dagworks/cli/templates/time_series_feature_engineering/components/__init__.py
dagworks/cli/templates/time_series_feature_engineering/components/_run.py
dagworks_sdk-0.7.0.dist-info/LICENSE
dagworks_sdk-0.7.0.dist-info/METADATA
dagworks_sdk-0.7.0.dist-info/WHEEL
dagworks_sdk-0.7.0.dist-info/entry_points.txt
dagworks_sdk-0.7.0.dist-info/top_level.txt
dagworks_sdk-0.7.0.dist-info/RECORD
