Metadata-Version: 2.2
Name: dagworks-sdk
Version: 0.7.0
Summary: DAGWorks SDK.
Author-email: Stefan Krawczyk <stefan@dagworks.io>, Elijah ben Izzy <elijah@dagworks.io>
Project-URL: Homepage, https://www.dagworks.io
Project-URL: Bug Reports, https://docs.google.com/forms/d/e/1FAIpQLScS9YvcuNOTretZWXUdur8XNcJPpkJwZwzxuGfbPJKc8IRS6A/viewform
Project-URL: Source, https://github.com/dagworks-inc/dagworks-sdk/
Project-URL: Documenation, https://docs.dagworks.io/
Keywords: hamilton,dagworks,observability
Classifier: Development Status :: 4 - Beta
Classifier: Intended Audience :: Developers
Classifier: Natural Language :: English
Classifier: Programming Language :: Python :: 3
Classifier: Programming Language :: Python :: 3.7
Classifier: Programming Language :: Python :: 3.8
Classifier: Programming Language :: Python :: 3.9
Classifier: Programming Language :: Python :: 3.10
Classifier: Programming Language :: Python :: 3.11
Requires-Python: <4,>=3.7
License-File: LICENSE
Requires-Dist: aiohttp
Requires-Dist: click
Requires-Dist: gitpython
Requires-Dist: posthog
Requires-Dist: requests
Requires-Dist: sf-hamilton>=1.43.0
Requires-Dist: sf-hamilton-sdk>=0.8.0
Requires-Dist: sqlglot
Provides-Extra: test
Requires-Dist: numpy<2.0.0; extra == "test"
Requires-Dist: polars; extra == "test"
Requires-Dist: pytest; extra == "test"
Requires-Dist: ray; extra == "test"
